[
    {
        "排名": "1",
        "用户名": " 23211835232 ",
        "姓名": "卷我是吧？ ",
        "班级": "\n\t\t\t\t\t23网工2",
        "解题": "17",
        "状态": " 49 ",
        "正确率": "36%",
        "代码行": "698"
    },
    {
        "排名": "2",
        "用户名": " 23211835203 ",
        "姓名": "小熊维尼 ",
        "班级": "\n\t\t\t\t\t23网工2",
        "解题": "6",
        "状态": " 6 ",
        "正确率": "100%",
        "代码行": "52"
    },
    {
        "排名": "3",
        "用户名": " 心上人是月亮 ",
        "姓名": "抱着瓜瓜睡觉 ",
        "班级": "\n\t\t\t\t\t23网工2",
        "解题": "5",
        "状态": " 8 ",
        "正确率": "87%",
        "代码行": "68"
    },
    {
        "排名": "4",
        "用户名": " 23211835216 ",
        "姓名": "陈宇轩 ",
        "班级": "\n\t\t\t\t\t23网工2",
        "解题": "2",
        "状态": " 5 ",
        "正确率": "40%",
        "代码行": "38"
    },
    {
        "排名": "5",
        "用户名": " 23211835225 ",
        "姓名": "徐欣怡 ",
        "班级": "\n\t\t\t\t\t23网工2",
        "解题": "1",
        "状态": " 1 ",
        "正确率": "100%",
        "代码行": "9"
    },
    {
        "排名": "6",
        "用户名": " 23211835234 ",
        "姓名": "王嘉凤 ",
        "班级": "\n\t\t\t\t\t23网工2",
        "解题": "1",
        "状态": " 2 ",
        "正确率": "50%",
        "代码行": "13"
    }
]